arl/AuthenticatedResourceLocator.py
arl/__init__.py
arl-1.0.1.dist-info/DESCRIPTION.rst
arl-1.0.1.dist-info/METADATA
arl-1.0.1.dist-info/RECORD
arl-1.0.1.dist-info/WHEEL
arl-1.0.1.dist-info/metadata.json
arl-1.0.1.dist-info/top_level.txt
arl-1.0.1.dist-info/zip-safe
