Metadata-Version: 2.0
Name: arl
Version: 1.0.1
Summary: Authenticated Resource Locator
Home-page: https://limacharlie.io
Author: Maxime Lamothe-Brassard ( Refraction Point, Inc )
Author-email: maxime@refractionpoint.com
License: Apache v2
Platform: UNKNOWN
Requires-Dist: gevent
Requires-Dist: google-cloud-storage
Requires-Dist: requests
